{
  "timestamp": "2026-06-21T20:22:14.219849+00:00",
  "summary": {
    "timestamp": "2026-06-21T20:22:14.219849+00:00",
    "regime": "BEAR",
    "regime_penalty": 0.55,
    "lp_score": null,
    "total_pools_scanned": 16320,
    "pools_after_filter": 26,
    "chains_scanned": [
      "Arbitrum",
      "BSC"
    ],
    "top_by_risk_adjusted": [
      {
        "chain": "BSC",
        "protocol": "uniswap-v3",
        "pool_address": "1f07f8d8-f405-450f-91eb-22537023004e",
        "symbol": "ZEC-WBNB",
        "token0": "ZEC",
        "token1": "WBNB",
        "fee_tier": 1.0,
        "tvl_usd": 148814,
        "volume_24h_usd": 126452.3588,
        "volume_7d_usd": 751925.53997,
        "apy_base": 310.15313,
        "apy_reward": 0,
        "apy_total": 310.15313,
        "il_risk": 0.5,
        "il_risk_label": "Medium",
        "risk_adjusted_apy": 224.86101924999997,
        "efficiency": 0.8497342911285228,
        "token0_type": "major",
        "token1_type": "major"
      },
      {
        "chain": "BSC",
        "protocol": "uniswap-v3",
        "pool_address": "9777c6f8-4447-48fe-9250-4be162a078ec",
        "symbol": "ZEC-USDT",
        "token0": "ZEC",
        "token1": "USDT",
        "fee_tier": 0.3,
        "tvl_usd": 752811,
        "volume_24h_usd": 441292.55536,
        "volume_7d_usd": 8028211.27142,
        "apy_base": 64.18812,
        "apy_reward": 0,
        "apy_total": 64.18812,
        "il_risk": 0.3,
        "il_risk_label": "Low",
        "risk_adjusted_apy": 53.59708019999999,
        "efficiency": 0.5861930223655074,
        "token0_type": "major",
        "token1_type": "stable"
      },
      {
        "chain": "BSC",
        "protocol": "uniswap-v3",
        "pool_address": "1f3942f4-9386-43a4-875a-e6c13a453d20",
        "symbol": "SOL-WBNB",
        "token0": "SOL",
        "token1": "WBNB",
        "fee_tier": 0.3,
        "tvl_usd": 284605,
        "volume_24h_usd": 192005.61486,
        "volume_7d_usd": 1082095.81327,
        "apy_base": 73.87307,
        "apy_reward": 0,
        "apy_total": 73.87307,
        "il_risk": 0.5,
        "il_risk_label": "Medium",
        "risk_adjusted_apy": 53.55797575,
        "efficiency": 0.6746389376855642,
        "token0_type": "major",
        "token1_type": "major"
      },
      {
        "chain": "Arbitrum",
        "protocol": "uniswap-v3",
        "pool_address": "18f93685-c199-44e7-8e25-154781d0a575",
        "symbol": "PENDLE-USDT",
        "token0": "PENDLE",
        "token1": "USDT",
        "fee_tier": 0.3,
        "tvl_usd": 490004,
        "volume_24h_usd": 236798.32863,
        "volume_7d_usd": 2964659.5524,
        "apy_base": 52.91673,
        "apy_reward": 0,
        "apy_total": 52.91673,
        "il_risk": 0.3,
        "il_risk_label": "Low",
        "risk_adjusted_apy": 44.18546955,
        "efficiency": 0.4832579502004065,
        "token0_type": "major",
        "token1_type": "stable"
      },
      {
        "chain": "BSC",
        "protocol": "uniswap-v3",
        "pool_address": "94b0665c-b74e-4d4b-9702-6276f4605dc8",
        "symbol": "WBNB-LINK",
        "token0": "WBNB",
        "token1": "LINK",
        "fee_tier": 0.3,
        "tvl_usd": 233040,
        "volume_24h_usd": 96860.58586,
        "volume_7d_usd": 660857.47493,
        "apy_base": 45.51259,
        "apy_reward": 0,
        "apy_total": 45.51259,
        "il_risk": 0.5,
        "il_risk_label": "Medium",
        "risk_adjusted_apy": 32.99662775,
        "efficiency": 0.41563931453827674,
        "token0_type": "major",
        "token1_type": "major"
      },
      {
        "chain": "Arbitrum",
        "protocol": "uniswap-v3",
        "pool_address": "a978c15f-c41a-433b-b02f-3434256ba66f",
        "symbol": "PENDLE-WETH",
        "token0": "PENDLE",
        "token1": "WETH",
        "fee_tier": 0.3,
        "tvl_usd": 991605,
        "volume_24h_usd": 355172.43252,
        "volume_7d_usd": 2401357.11848,
        "apy_base": 39.22065,
        "apy_reward": 0,
        "apy_total": 39.22065,
        "il_risk": 0.5,
        "il_risk_label": "Medium",
        "risk_adjusted_apy": 28.43497125,
        "efficiency": 0.3581793481476999,
        "token0_type": "major",
        "token1_type": "major"
      },
      {
        "chain": "Arbitrum",
        "protocol": "uniswap-v3",
        "pool_address": "c4f27457-0d3d-4f6d-8c3e-eb1a0e6e91b8",
        "symbol": "PENDLE-WETH",
        "token0": "PENDLE",
        "token1": "WETH",
        "fee_tier": 0.05,
        "tvl_usd": 130320,
        "volume_24h_usd": 170585.10568,
        "volume_7d_usd": 1110781.27743,
        "apy_base": 23.88873,
        "apy_reward": 0,
        "apy_total": 23.88873,
        "il_risk": 0.5,
        "il_risk_label": "Medium",
        "risk_adjusted_apy": 17.31932925,
        "efficiency": 1.3089710380601596,
        "token0_type": "major",
        "token1_type": "major"
      },
      {
        "chain": "Arbitrum",
        "protocol": "uniswap-v3",
        "pool_address": "eb782bdd-b9a5-4522-914d-285049ce9e9f",
        "symbol": "WETH-UNI",
        "token0": "WETH",
        "token1": "UNI",
        "fee_tier": 0.3,
        "tvl_usd": 261942,
        "volume_24h_usd": 56980.87841,
        "volume_7d_usd": 1378762.88499,
        "apy_base": 23.81977,
        "apy_reward": 0,
        "apy_total": 23.81977,
        "il_risk": 0.5,
        "il_risk_label": "Medium",
        "risk_adjusted_apy": 17.26933325,
        "efficiency": 0.2175324247734231,
        "token0_type": "major",
        "token1_type": "major"
      },
      {
        "chain": "BSC",
        "protocol": "uniswap-v3",
        "pool_address": "f52993c8-fdad-40cb-adde-797b383034c5",
        "symbol": "USDT-WBNB",
        "token0": "USDT",
        "token1": "WBNB",
        "fee_tier": 0.05,
        "tvl_usd": 3721957,
        "volume_24h_usd": 4210078.95266,
        "volume_7d_usd": 61532407.68141,
        "apy_base": 20.64342,
        "apy_reward": 0,
        "apy_total": 20.64342,
        "il_risk": 0.3,
        "il_risk_label": "Low",
        "risk_adjusted_apy": 17.2372557,
        "efficiency": 1.1311465856967182,
        "token0_type": "stable",
        "token1_type": "major"
      },
      {
        "chain": "Arbitrum",
        "protocol": "uniswap-v3",
        "pool_address": "090bbc01-1bfb-435d-b928-58ea9bdc8a25",
        "symbol": "PENDLE-USDC",
        "token0": "PENDLE",
        "token1": "USDC",
        "fee_tier": 0.3,
        "tvl_usd": 335816,
        "volume_24h_usd": 50934.5533,
        "volume_7d_usd": 470781.85976,
        "apy_base": 16.60828,
        "apy_reward": 0,
        "apy_total": 16.60828,
        "il_risk": 0.3,
        "il_risk_label": "Low",
        "risk_adjusted_apy": 13.8679138,
        "efficiency": 0.15167399200752793,
        "token0_type": "major",
        "token1_type": "stable"
      }
    ],
    "top_by_raw_apy": [
      {
        "chain": "BSC",
        "protocol": "uniswap-v3",
        "pool_address": "1f07f8d8-f405-450f-91eb-22537023004e",
        "symbol": "ZEC-WBNB",
        "token0": "ZEC",
        "token1": "WBNB",
        "fee_tier": 1.0,
        "tvl_usd": 148814,
        "volume_24h_usd": 126452.3588,
        "volume_7d_usd": 751925.53997,
        "apy_base": 310.15313,
        "apy_reward": 0,
        "apy_total": 310.15313,
        "il_risk": 0.5,
        "il_risk_label": "Medium",
        "risk_adjusted_apy": 224.86101924999997,
        "efficiency": 0.8497342911285228,
        "token0_type": "major",
        "token1_type": "major"
      },
      {
        "chain": "BSC",
        "protocol": "uniswap-v3",
        "pool_address": "1f3942f4-9386-43a4-875a-e6c13a453d20",
        "symbol": "SOL-WBNB",
        "token0": "SOL",
        "token1": "WBNB",
        "fee_tier": 0.3,
        "tvl_usd": 284605,
        "volume_24h_usd": 192005.61486,
        "volume_7d_usd": 1082095.81327,
        "apy_base": 73.87307,
        "apy_reward": 0,
        "apy_total": 73.87307,
        "il_risk": 0.5,
        "il_risk_label": "Medium",
        "risk_adjusted_apy": 53.55797575,
        "efficiency": 0.6746389376855642,
        "token0_type": "major",
        "token1_type": "major"
      },
      {
        "chain": "BSC",
        "protocol": "uniswap-v3",
        "pool_address": "9777c6f8-4447-48fe-9250-4be162a078ec",
        "symbol": "ZEC-USDT",
        "token0": "ZEC",
        "token1": "USDT",
        "fee_tier": 0.3,
        "tvl_usd": 752811,
        "volume_24h_usd": 441292.55536,
        "volume_7d_usd": 8028211.27142,
        "apy_base": 64.18812,
        "apy_reward": 0,
        "apy_total": 64.18812,
        "il_risk": 0.3,
        "il_risk_label": "Low",
        "risk_adjusted_apy": 53.59708019999999,
        "efficiency": 0.5861930223655074,
        "token0_type": "major",
        "token1_type": "stable"
      },
      {
        "chain": "Arbitrum",
        "protocol": "uniswap-v3",
        "pool_address": "18f93685-c199-44e7-8e25-154781d0a575",
        "symbol": "PENDLE-USDT",
        "token0": "PENDLE",
        "token1": "USDT",
        "fee_tier": 0.3,
        "tvl_usd": 490004,
        "volume_24h_usd": 236798.32863,
        "volume_7d_usd": 2964659.5524,
        "apy_base": 52.91673,
        "apy_reward": 0,
        "apy_total": 52.91673,
        "il_risk": 0.3,
        "il_risk_label": "Low",
        "risk_adjusted_apy": 44.18546955,
        "efficiency": 0.4832579502004065,
        "token0_type": "major",
        "token1_type": "stable"
      },
      {
        "chain": "BSC",
        "protocol": "uniswap-v3",
        "pool_address": "94b0665c-b74e-4d4b-9702-6276f4605dc8",
        "symbol": "WBNB-LINK",
        "token0": "WBNB",
        "token1": "LINK",
        "fee_tier": 0.3,
        "tvl_usd": 233040,
        "volume_24h_usd": 96860.58586,
        "volume_7d_usd": 660857.47493,
        "apy_base": 45.51259,
        "apy_reward": 0,
        "apy_total": 45.51259,
        "il_risk": 0.5,
        "il_risk_label": "Medium",
        "risk_adjusted_apy": 32.99662775,
        "efficiency": 0.41563931453827674,
        "token0_type": "major",
        "token1_type": "major"
      },
      {
        "chain": "Arbitrum",
        "protocol": "uniswap-v3",
        "pool_address": "a978c15f-c41a-433b-b02f-3434256ba66f",
        "symbol": "PENDLE-WETH",
        "token0": "PENDLE",
        "token1": "WETH",
        "fee_tier": 0.3,
        "tvl_usd": 991605,
        "volume_24h_usd": 355172.43252,
        "volume_7d_usd": 2401357.11848,
        "apy_base": 39.22065,
        "apy_reward": 0,
        "apy_total": 39.22065,
        "il_risk": 0.5,
        "il_risk_label": "Medium",
        "risk_adjusted_apy": 28.43497125,
        "efficiency": 0.3581793481476999,
        "token0_type": "major",
        "token1_type": "major"
      },
      {
        "chain": "Arbitrum",
        "protocol": "uniswap-v3",
        "pool_address": "c4f27457-0d3d-4f6d-8c3e-eb1a0e6e91b8",
        "symbol": "PENDLE-WETH",
        "token0": "PENDLE",
        "token1": "WETH",
        "fee_tier": 0.05,
        "tvl_usd": 130320,
        "volume_24h_usd": 170585.10568,
        "volume_7d_usd": 1110781.27743,
        "apy_base": 23.88873,
        "apy_reward": 0,
        "apy_total": 23.88873,
        "il_risk": 0.5,
        "il_risk_label": "Medium",
        "risk_adjusted_apy": 17.31932925,
        "efficiency": 1.3089710380601596,
        "token0_type": "major",
        "token1_type": "major"
      },
      {
        "chain": "Arbitrum",
        "protocol": "uniswap-v3",
        "pool_address": "eb782bdd-b9a5-4522-914d-285049ce9e9f",
        "symbol": "WETH-UNI",
        "token0": "WETH",
        "token1": "UNI",
        "fee_tier": 0.3,
        "tvl_usd": 261942,
        "volume_24h_usd": 56980.87841,
        "volume_7d_usd": 1378762.88499,
        "apy_base": 23.81977,
        "apy_reward": 0,
        "apy_total": 23.81977,
        "il_risk": 0.5,
        "il_risk_label": "Medium",
        "risk_adjusted_apy": 17.26933325,
        "efficiency": 0.2175324247734231,
        "token0_type": "major",
        "token1_type": "major"
      },
      {
        "chain": "BSC",
        "protocol": "uniswap-v3",
        "pool_address": "f52993c8-fdad-40cb-adde-797b383034c5",
        "symbol": "USDT-WBNB",
        "token0": "USDT",
        "token1": "WBNB",
        "fee_tier": 0.05,
        "tvl_usd": 3721957,
        "volume_24h_usd": 4210078.95266,
        "volume_7d_usd": 61532407.68141,
        "apy_base": 20.64342,
        "apy_reward": 0,
        "apy_total": 20.64342,
        "il_risk": 0.3,
        "il_risk_label": "Low",
        "risk_adjusted_apy": 17.2372557,
        "efficiency": 1.1311465856967182,
        "token0_type": "stable",
        "token1_type": "major"
      },
      {
        "chain": "Arbitrum",
        "protocol": "uniswap-v3",
        "pool_address": "090bbc01-1bfb-435d-b928-58ea9bdc8a25",
        "symbol": "PENDLE-USDC",
        "token0": "PENDLE",
        "token1": "USDC",
        "fee_tier": 0.3,
        "tvl_usd": 335816,
        "volume_24h_usd": 50934.5533,
        "volume_7d_usd": 470781.85976,
        "apy_base": 16.60828,
        "apy_reward": 0,
        "apy_total": 16.60828,
        "il_risk": 0.3,
        "il_risk_label": "Low",
        "risk_adjusted_apy": 13.8679138,
        "efficiency": 0.15167399200752793,
        "token0_type": "major",
        "token1_type": "stable"
      }
    ],
    "top_by_tvl": [
      {
        "chain": "Arbitrum",
        "protocol": "uniswap-v3",
        "pool_address": "a14bd201-764c-40a5-86b8-2928b2461232",
        "symbol": "WETH-USDC",
        "token0": "WETH",
        "token1": "USDC",
        "fee_tier": 0.05,
        "tvl_usd": 35416952,
        "volume_24h_usd": 14229380.59167,
        "volume_7d_usd": 277156217.64902,
        "apy_base": 7.33226,
        "apy_reward": 0,
        "apy_total": 7.33226,
        "il_risk": 0.3,
        "il_risk_label": "Low",
        "risk_adjusted_apy": 6.1224371,
        "efficiency": 0.4017675092896193,
        "token0_type": "major",
        "token1_type": "stable"
      },
      {
        "chain": "Arbitrum",
        "protocol": "uniswap-v3",
        "pool_address": "bb7e9353-129f-4e01-b822-f4250d0abb8a",
        "symbol": "WBTC-WETH",
        "token0": "WBTC",
        "token1": "WETH",
        "fee_tier": 0.05,
        "tvl_usd": 31105534,
        "volume_24h_usd": 9601330.1096,
        "volume_7d_usd": 188530670.12686,
        "apy_base": 5.63322,
        "apy_reward": 0,
        "apy_total": 5.63322,
        "il_risk": 0.5,
        "il_risk_label": "Medium",
        "risk_adjusted_apy": 4.0840844999999995,
        "efficiency": 0.3086695155145062,
        "token0_type": "major",
        "token1_type": "major"
      },
      {
        "chain": "Arbitrum",
        "protocol": "uniswap-v3",
        "pool_address": "7127db96-afba-4089-8c9d-daa93c116856",
        "symbol": "WBTC-USDC",
        "token0": "WBTC",
        "token1": "USDC",
        "fee_tier": 0.05,
        "tvl_usd": 9375777,
        "volume_24h_usd": 3101530.29174,
        "volume_7d_usd": 61857436.54662,
        "apy_base": 6.03715,
        "apy_reward": 0,
        "apy_total": 6.03715,
        "il_risk": 0.3,
        "il_risk_label": "Low",
        "risk_adjusted_apy": 5.04102025,
        "efficiency": 0.33080248087598496,
        "token0_type": "major",
        "token1_type": "stable"
      },
      {
        "chain": "Arbitrum",
        "protocol": "uniswap-v3",
        "pool_address": "af3cd3a9-a9b8-483e-82c6-bf4fceb66584",
        "symbol": "WBTC-USDT",
        "token0": "WBTC",
        "token1": "USDT",
        "fee_tier": 0.05,
        "tvl_usd": 8717812,
        "volume_24h_usd": 3373426.68993,
        "volume_7d_usd": 67321697.736,
        "apy_base": 7.06198,
        "apy_reward": 0,
        "apy_total": 7.06198,
        "il_risk": 0.3,
        "il_risk_label": "Low",
        "risk_adjusted_apy": 5.8967533,
        "efficiency": 0.38695795343258144,
        "token0_type": "major",
        "token1_type": "stable"
      },
      {
        "chain": "Arbitrum",
        "protocol": "uniswap-v3",
        "pool_address": "49bdce2c-65d0-4bb7-bdc0-dc0d642317e6",
        "symbol": "WETH-USDT",
        "token0": "WETH",
        "token1": "USDT",
        "fee_tier": 0.05,
        "tvl_usd": 6672435,
        "volume_24h_usd": 1477878.40263,
        "volume_7d_usd": 32685342.60548,
        "apy_base": 4.04219,
        "apy_reward": 0,
        "apy_total": 4.04219,
        "il_risk": 0.3,
        "il_risk_label": "Low",
        "risk_adjusted_apy": 3.3752286499999995,
        "efficiency": 0.22149011607156907,
        "token0_type": "major",
        "token1_type": "stable"
      },
      {
        "chain": "Arbitrum",
        "protocol": "uniswap-v3",
        "pool_address": "94594b8f-fd0c-48c3-b760-87c8e56b64fa",
        "symbol": "WETH-USDC",
        "token0": "WETH",
        "token1": "USDC",
        "fee_tier": 0.3,
        "tvl_usd": 5754314,
        "volume_24h_usd": 293385.23874,
        "volume_7d_usd": 8070349.52638,
        "apy_base": 5.58289,
        "apy_reward": 0,
        "apy_total": 5.58289,
        "il_risk": 0.3,
        "il_risk_label": "Low",
        "risk_adjusted_apy": 4.66171315,
        "efficiency": 0.0509852675297177,
        "token0_type": "major",
        "token1_type": "stable"
      },
      {
        "chain": "BSC",
        "protocol": "uniswap-v3",
        "pool_address": "5bec56fa-fa61-4f9e-b454-dd06df68b876",
        "symbol": "BTCB-WBNB",
        "token0": "BTCB",
        "token1": "WBNB",
        "fee_tier": 0.05,
        "tvl_usd": 5659422,
        "volume_24h_usd": 3185075.26262,
        "volume_7d_usd": 34872954.51179,
        "apy_base": 10.27095,
        "apy_reward": 0,
        "apy_total": 10.27095,
        "il_risk": 0.5,
        "il_risk_label": "Medium",
        "risk_adjusted_apy": 7.4464387499999996,
        "efficiency": 0.5627916176987685,
        "token0_type": "major",
        "token1_type": "major"
      },
      {
        "chain": "BSC",
        "protocol": "uniswap-v3",
        "pool_address": "f52993c8-fdad-40cb-adde-797b383034c5",
        "symbol": "USDT-WBNB",
        "token0": "USDT",
        "token1": "WBNB",
        "fee_tier": 0.05,
        "tvl_usd": 3721957,
        "volume_24h_usd": 4210078.95266,
        "volume_7d_usd": 61532407.68141,
        "apy_base": 20.64342,
        "apy_reward": 0,
        "apy_total": 20.64342,
        "il_risk": 0.3,
        "il_risk_label": "Low",
        "risk_adjusted_apy": 17.2372557,
        "efficiency": 1.1311465856967182,
        "token0_type": "stable",
        "token1_type": "major"
      },
      {
        "chain": "BSC",
        "protocol": "uniswap-v3",
        "pool_address": "a0a4cf75-ccd3-4ec3-a7d3-79ca59d33646",
        "symbol": "ETH-WBNB",
        "token0": "ETH",
        "token1": "WBNB",
        "fee_tier": 0.05,
        "tvl_usd": 3701322,
        "volume_24h_usd": 2658343.26408,
        "volume_7d_usd": 25180339.69796,
        "apy_base": 13.10742,
        "apy_reward": 0,
        "apy_total": 13.10742,
        "il_risk": 0.5,
        "il_risk_label": "Medium",
        "risk_adjusted_apy": 9.502879499999999,
        "efficiency": 0.7182145363413397,
        "token0_type": "major",
        "token1_type": "major"
      },
      {
        "chain": "BSC",
        "protocol": "uniswap-v3",
        "pool_address": "6b928a97-3519-4cf4-a0e2-c91f34e719db",
        "symbol": "USDT-BTCB",
        "token0": "USDT",
        "token1": "BTCB",
        "fee_tier": 0.05,
        "tvl_usd": 2166142,
        "volume_24h_usd": 1012962.98257,
        "volume_7d_usd": 14967835.12973,
        "apy_base": 8.53433,
        "apy_reward": 0,
        "apy_total": 8.53433,
        "il_risk": 0.3,
        "il_risk_label": "Low",
        "risk_adjusted_apy": 7.1261655500000005,
        "efficiency": 0.4676346160916505,
        "token0_type": "stable",
        "token1_type": "major"
      }
    ]
  },
  "all_opportunities": [
    {
      "chain": "Arbitrum",
      "protocol": "uniswap-v3",
      "pool_address": "a14bd201-764c-40a5-86b8-2928b2461232",
      "symbol": "WETH-USDC",
      "token0": "WETH",
      "token1": "USDC",
      "fee_tier": 0.05,
      "tvl_usd": 35416952,
      "volume_24h_usd": 14229380.59167,
      "volume_7d_usd": 277156217.64902,
      "apy_base": 7.33226,
      "apy_reward": 0,
      "apy_total": 7.33226,
      "il_risk": 0.3,
      "il_risk_label": "Low",
      "risk_adjusted_apy": 6.1224371,
      "efficiency": 0.4017675092896193,
      "token0_type": "major",
      "token1_type": "stable"
    },
    {
      "chain": "Arbitrum",
      "protocol": "uniswap-v3",
      "pool_address": "bb7e9353-129f-4e01-b822-f4250d0abb8a",
      "symbol": "WBTC-WETH",
      "token0": "WBTC",
      "token1": "WETH",
      "fee_tier": 0.05,
      "tvl_usd": 31105534,
      "volume_24h_usd": 9601330.1096,
      "volume_7d_usd": 188530670.12686,
      "apy_base": 5.63322,
      "apy_reward": 0,
      "apy_total": 5.63322,
      "il_risk": 0.5,
      "il_risk_label": "Medium",
      "risk_adjusted_apy": 4.0840844999999995,
      "efficiency": 0.3086695155145062,
      "token0_type": "major",
      "token1_type": "major"
    },
    {
      "chain": "Arbitrum",
      "protocol": "uniswap-v3",
      "pool_address": "7127db96-afba-4089-8c9d-daa93c116856",
      "symbol": "WBTC-USDC",
      "token0": "WBTC",
      "token1": "USDC",
      "fee_tier": 0.05,
      "tvl_usd": 9375777,
      "volume_24h_usd": 3101530.29174,
      "volume_7d_usd": 61857436.54662,
      "apy_base": 6.03715,
      "apy_reward": 0,
      "apy_total": 6.03715,
      "il_risk": 0.3,
      "il_risk_label": "Low",
      "risk_adjusted_apy": 5.04102025,
      "efficiency": 0.33080248087598496,
      "token0_type": "major",
      "token1_type": "stable"
    },
    {
      "chain": "Arbitrum",
      "protocol": "uniswap-v3",
      "pool_address": "af3cd3a9-a9b8-483e-82c6-bf4fceb66584",
      "symbol": "WBTC-USDT",
      "token0": "WBTC",
      "token1": "USDT",
      "fee_tier": 0.05,
      "tvl_usd": 8717812,
      "volume_24h_usd": 3373426.68993,
      "volume_7d_usd": 67321697.736,
      "apy_base": 7.06198,
      "apy_reward": 0,
      "apy_total": 7.06198,
      "il_risk": 0.3,
      "il_risk_label": "Low",
      "risk_adjusted_apy": 5.8967533,
      "efficiency": 0.38695795343258144,
      "token0_type": "major",
      "token1_type": "stable"
    },
    {
      "chain": "Arbitrum",
      "protocol": "uniswap-v3",
      "pool_address": "49bdce2c-65d0-4bb7-bdc0-dc0d642317e6",
      "symbol": "WETH-USDT",
      "token0": "WETH",
      "token1": "USDT",
      "fee_tier": 0.05,
      "tvl_usd": 6672435,
      "volume_24h_usd": 1477878.40263,
      "volume_7d_usd": 32685342.60548,
      "apy_base": 4.04219,
      "apy_reward": 0,
      "apy_total": 4.04219,
      "il_risk": 0.3,
      "il_risk_label": "Low",
      "risk_adjusted_apy": 3.3752286499999995,
      "efficiency": 0.22149011607156907,
      "token0_type": "major",
      "token1_type": "stable"
    },
    {
      "chain": "Arbitrum",
      "protocol": "uniswap-v3",
      "pool_address": "94594b8f-fd0c-48c3-b760-87c8e56b64fa",
      "symbol": "WETH-USDC",
      "token0": "WETH",
      "token1": "USDC",
      "fee_tier": 0.3,
      "tvl_usd": 5754314,
      "volume_24h_usd": 293385.23874,
      "volume_7d_usd": 8070349.52638,
      "apy_base": 5.58289,
      "apy_reward": 0,
      "apy_total": 5.58289,
      "il_risk": 0.3,
      "il_risk_label": "Low",
      "risk_adjusted_apy": 4.66171315,
      "efficiency": 0.0509852675297177,
      "token0_type": "major",
      "token1_type": "stable"
    },
    {
      "chain": "BSC",
      "protocol": "uniswap-v3",
      "pool_address": "5bec56fa-fa61-4f9e-b454-dd06df68b876",
      "symbol": "BTCB-WBNB",
      "token0": "BTCB",
      "token1": "WBNB",
      "fee_tier": 0.05,
      "tvl_usd": 5659422,
      "volume_24h_usd": 3185075.26262,
      "volume_7d_usd": 34872954.51179,
      "apy_base": 10.27095,
      "apy_reward": 0,
      "apy_total": 10.27095,
      "il_risk": 0.5,
      "il_risk_label": "Medium",
      "risk_adjusted_apy": 7.4464387499999996,
      "efficiency": 0.5627916176987685,
      "token0_type": "major",
      "token1_type": "major"
    },
    {
      "chain": "BSC",
      "protocol": "uniswap-v3",
      "pool_address": "f52993c8-fdad-40cb-adde-797b383034c5",
      "symbol": "USDT-WBNB",
      "token0": "USDT",
      "token1": "WBNB",
      "fee_tier": 0.05,
      "tvl_usd": 3721957,
      "volume_24h_usd": 4210078.95266,
      "volume_7d_usd": 61532407.68141,
      "apy_base": 20.64342,
      "apy_reward": 0,
      "apy_total": 20.64342,
      "il_risk": 0.3,
      "il_risk_label": "Low",
      "risk_adjusted_apy": 17.2372557,
      "efficiency": 1.1311465856967182,
      "token0_type": "stable",
      "token1_type": "major"
    },
    {
      "chain": "BSC",
      "protocol": "uniswap-v3",
      "pool_address": "a0a4cf75-ccd3-4ec3-a7d3-79ca59d33646",
      "symbol": "ETH-WBNB",
      "token0": "ETH",
      "token1": "WBNB",
      "fee_tier": 0.05,
      "tvl_usd": 3701322,
      "volume_24h_usd": 2658343.26408,
      "volume_7d_usd": 25180339.69796,
      "apy_base": 13.10742,
      "apy_reward": 0,
      "apy_total": 13.10742,
      "il_risk": 0.5,
      "il_risk_label": "Medium",
      "risk_adjusted_apy": 9.502879499999999,
      "efficiency": 0.7182145363413397,
      "token0_type": "major",
      "token1_type": "major"
    },
    {
      "chain": "BSC",
      "protocol": "uniswap-v3",
      "pool_address": "6b928a97-3519-4cf4-a0e2-c91f34e719db",
      "symbol": "USDT-BTCB",
      "token0": "USDT",
      "token1": "BTCB",
      "fee_tier": 0.05,
      "tvl_usd": 2166142,
      "volume_24h_usd": 1012962.98257,
      "volume_7d_usd": 14967835.12973,
      "apy_base": 8.53433,
      "apy_reward": 0,
      "apy_total": 8.53433,
      "il_risk": 0.3,
      "il_risk_label": "Low",
      "risk_adjusted_apy": 7.1261655500000005,
      "efficiency": 0.4676346160916505,
      "token0_type": "stable",
      "token1_type": "major"
    },
    {
      "chain": "BSC",
      "protocol": "uniswap-v3",
      "pool_address": "c9079f69-c269-4d2f-b96b-321e22f67cf8",
      "symbol": "ZEC-BTCB",
      "token0": "ZEC",
      "token1": "BTCB",
      "fee_tier": 0.3,
      "tvl_usd": 1584527,
      "volume_24h_usd": 162340.48449,
      "volume_7d_usd": 2865461.86865,
      "apy_base": 11.21867,
      "apy_reward": 0,
      "apy_total": 11.21867,
      "il_risk": 0.5,
      "il_risk_label": "Medium",
      "risk_adjusted_apy": 8.13353575,
      "efficiency": 0.10245359308487643,
      "token0_type": "major",
      "token1_type": "major"
    },
    {
      "chain": "Arbitrum",
      "protocol": "uniswap-v3",
      "pool_address": "a978c15f-c41a-433b-b02f-3434256ba66f",
      "symbol": "PENDLE-WETH",
      "token0": "PENDLE",
      "token1": "WETH",
      "fee_tier": 0.3,
      "tvl_usd": 991605,
      "volume_24h_usd": 355172.43252,
      "volume_7d_usd": 2401357.11848,
      "apy_base": 39.22065,
      "apy_reward": 0,
      "apy_total": 39.22065,
      "il_risk": 0.5,
      "il_risk_label": "Medium",
      "risk_adjusted_apy": 28.43497125,
      "efficiency": 0.3581793481476999,
      "token0_type": "major",
      "token1_type": "major"
    },
    {
      "chain": "Arbitrum",
      "protocol": "uniswap-v3",
      "pool_address": "9fb44210-2b23-4b7d-8f2f-aba82b93843e",
      "symbol": "WETH-USDC.E",
      "token0": "WETH",
      "token1": "USDC.E",
      "fee_tier": 0.05,
      "tvl_usd": 932405,
      "volume_24h_usd": 203881.96528,
      "volume_7d_usd": 3471224.99094,
      "apy_base": 3.99059,
      "apy_reward": 0,
      "apy_total": 3.99059,
      "il_risk": 0.3,
      "il_risk_label": "Low",
      "risk_adjusted_apy": 3.3321426499999998,
      "efficiency": 0.2186624538478451,
      "token0_type": "major",
      "token1_type": "stable"
    },
    {
      "chain": "BSC",
      "protocol": "uniswap-v3",
      "pool_address": "a8a67ce9-3f86-4272-a305-d4b2abd58783",
      "symbol": "ETH-BTCB",
      "token0": "ETH",
      "token1": "BTCB",
      "fee_tier": 0.3,
      "tvl_usd": 757305,
      "volume_24h_usd": 68135.06916,
      "volume_7d_usd": 1133899.78872,
      "apy_base": 9.85176,
      "apy_reward": 0,
      "apy_total": 9.85176,
      "il_risk": 0.5,
      "il_risk_label": "Medium",
      "risk_adjusted_apy": 7.142526,
      "efficiency": 0.0899704467288609,
      "token0_type": "major",
      "token1_type": "major"
    },
    {
      "chain": "BSC",
      "protocol": "uniswap-v3",
      "pool_address": "9777c6f8-4447-48fe-9250-4be162a078ec",
      "symbol": "ZEC-USDT",
      "token0": "ZEC",
      "token1": "USDT",
      "fee_tier": 0.3,
      "tvl_usd": 752811,
      "volume_24h_usd": 441292.55536,
      "volume_7d_usd": 8028211.27142,
      "apy_base": 64.18812,
      "apy_reward": 0,
      "apy_total": 64.18812,
      "il_risk": 0.3,
      "il_risk_label": "Low",
      "risk_adjusted_apy": 53.59708019999999,
      "efficiency": 0.5861930223655074,
      "token0_type": "major",
      "token1_type": "stable"
    },
    {
      "chain": "Arbitrum",
      "protocol": "uniswap-v3",
      "pool_address": "18f93685-c199-44e7-8e25-154781d0a575",
      "symbol": "PENDLE-USDT",
      "token0": "PENDLE",
      "token1": "USDT",
      "fee_tier": 0.3,
      "tvl_usd": 490004,
      "volume_24h_usd": 236798.32863,
      "volume_7d_usd": 2964659.5524,
      "apy_base": 52.91673,
      "apy_reward": 0,
      "apy_total": 52.91673,
      "il_risk": 0.3,
      "il_risk_label": "Low",
      "risk_adjusted_apy": 44.18546955,
      "efficiency": 0.4832579502004065,
      "token0_type": "major",
      "token1_type": "stable"
    },
    {
      "chain": "BSC",
      "protocol": "uniswap-v3",
      "pool_address": "490d8825-a5af-405a-9c72-4e100b18b0c0",
      "symbol": "USDT-USDC",
      "token0": "USDT",
      "token1": "USDC",
      "fee_tier": 0.01,
      "tvl_usd": 471808,
      "volume_24h_usd": 148455.19875,
      "volume_7d_usd": 2279162.91206,
      "apy_base": 1.14848,
      "apy_reward": 0,
      "apy_total": 1.14848,
      "il_risk": 0.0,
      "il_risk_label": "Very Low",
      "risk_adjusted_apy": 1.14848,
      "efficiency": 0.31465172008528897,
      "token0_type": "stable",
      "token1_type": "stable"
    },
    {
      "chain": "BSC",
      "protocol": "uniswap-v3",
      "pool_address": "c065d271-b808-49c9-815c-ec75a96a4833",
      "symbol": "USDT-WBNB",
      "token0": "USDT",
      "token1": "WBNB",
      "fee_tier": 0.01,
      "tvl_usd": 406044,
      "volume_24h_usd": 357596.66243,
      "volume_7d_usd": 7433391.84208,
      "apy_base": 3.2145,
      "apy_reward": 0,
      "apy_total": 3.2145,
      "il_risk": 0.3,
      "il_risk_label": "Low",
      "risk_adjusted_apy": 2.6841075,
      "efficiency": 0.8806845130823261,
      "token0_type": "stable",
      "token1_type": "major"
    },
    {
      "chain": "Arbitrum",
      "protocol": "uniswap-v3",
      "pool_address": "090bbc01-1bfb-435d-b928-58ea9bdc8a25",
      "symbol": "PENDLE-USDC",
      "token0": "PENDLE",
      "token1": "USDC",
      "fee_tier": 0.3,
      "tvl_usd": 335816,
      "volume_24h_usd": 50934.5533,
      "volume_7d_usd": 470781.85976,
      "apy_base": 16.60828,
      "apy_reward": 0,
      "apy_total": 16.60828,
      "il_risk": 0.3,
      "il_risk_label": "Low",
      "risk_adjusted_apy": 13.8679138,
      "efficiency": 0.15167399200752793,
      "token0_type": "major",
      "token1_type": "stable"
    },
    {
      "chain": "BSC",
      "protocol": "uniswap-v3",
      "pool_address": "1f3942f4-9386-43a4-875a-e6c13a453d20",
      "symbol": "SOL-WBNB",
      "token0": "SOL",
      "token1": "WBNB",
      "fee_tier": 0.3,
      "tvl_usd": 284605,
      "volume_24h_usd": 192005.61486,
      "volume_7d_usd": 1082095.81327,
      "apy_base": 73.87307,
      "apy_reward": 0,
      "apy_total": 73.87307,
      "il_risk": 0.5,
      "il_risk_label": "Medium",
      "risk_adjusted_apy": 53.55797575,
      "efficiency": 0.6746389376855642,
      "token0_type": "major",
      "token1_type": "major"
    },
    {
      "chain": "Arbitrum",
      "protocol": "uniswap-v3",
      "pool_address": "eb782bdd-b9a5-4522-914d-285049ce9e9f",
      "symbol": "WETH-UNI",
      "token0": "WETH",
      "token1": "UNI",
      "fee_tier": 0.3,
      "tvl_usd": 261942,
      "volume_24h_usd": 56980.87841,
      "volume_7d_usd": 1378762.88499,
      "apy_base": 23.81977,
      "apy_reward": 0,
      "apy_total": 23.81977,
      "il_risk": 0.5,
      "il_risk_label": "Medium",
      "risk_adjusted_apy": 17.26933325,
      "efficiency": 0.2175324247734231,
      "token0_type": "major",
      "token1_type": "major"
    },
    {
      "chain": "Arbitrum",
      "protocol": "uniswap-v3",
      "pool_address": "fad38baa-78b7-410b-b72b-5db39b7f6f51",
      "symbol": "WETH-LINK",
      "token0": "WETH",
      "token1": "LINK",
      "fee_tier": 0.05,
      "tvl_usd": 258593,
      "volume_24h_usd": 175152.71777,
      "volume_7d_usd": 2634661.41414,
      "apy_base": 12.36126,
      "apy_reward": 0,
      "apy_total": 12.36126,
      "il_risk": 0.5,
      "il_risk_label": "Medium",
      "risk_adjusted_apy": 8.9619135,
      "efficiency": 0.677329694809991,
      "token0_type": "major",
      "token1_type": "major"
    },
    {
      "chain": "BSC",
      "protocol": "uniswap-v3",
      "pool_address": "94b0665c-b74e-4d4b-9702-6276f4605dc8",
      "symbol": "WBNB-LINK",
      "token0": "WBNB",
      "token1": "LINK",
      "fee_tier": 0.3,
      "tvl_usd": 233040,
      "volume_24h_usd": 96860.58586,
      "volume_7d_usd": 660857.47493,
      "apy_base": 45.51259,
      "apy_reward": 0,
      "apy_total": 45.51259,
      "il_risk": 0.5,
      "il_risk_label": "Medium",
      "risk_adjusted_apy": 32.99662775,
      "efficiency": 0.41563931453827674,
      "token0_type": "major",
      "token1_type": "major"
    },
    {
      "chain": "BSC",
      "protocol": "uniswap-v3",
      "pool_address": "1f07f8d8-f405-450f-91eb-22537023004e",
      "symbol": "ZEC-WBNB",
      "token0": "ZEC",
      "token1": "WBNB",
      "fee_tier": 1.0,
      "tvl_usd": 148814,
      "volume_24h_usd": 126452.3588,
      "volume_7d_usd": 751925.53997,
      "apy_base": 310.15313,
      "apy_reward": 0,
      "apy_total": 310.15313,
      "il_risk": 0.5,
      "il_risk_label": "Medium",
      "risk_adjusted_apy": 224.86101924999997,
      "efficiency": 0.8497342911285228,
      "token0_type": "major",
      "token1_type": "major"
    },
    {
      "chain": "Arbitrum",
      "protocol": "uniswap-v3",
      "pool_address": "2ec84b50-59e5-49e6-ab12-41e99ed32a8c",
      "symbol": "WSTETH-WETH",
      "token0": "WSTETH",
      "token1": "WETH",
      "fee_tier": 0.01,
      "tvl_usd": 144998,
      "volume_24h_usd": 58476.36797,
      "volume_7d_usd": 1564960.31173,
      "apy_base": 1.47201,
      "apy_reward": 0,
      "apy_total": 1.47201,
      "il_risk": 0.5,
      "il_risk_label": "Medium",
      "risk_adjusted_apy": 1.06720725,
      "efficiency": 0.4032908589773652,
      "token0_type": "major",
      "token1_type": "major"
    },
    {
      "chain": "Arbitrum",
      "protocol": "uniswap-v3",
      "pool_address": "c4f27457-0d3d-4f6d-8c3e-eb1a0e6e91b8",
      "symbol": "PENDLE-WETH",
      "token0": "PENDLE",
      "token1": "WETH",
      "fee_tier": 0.05,
      "tvl_usd": 130320,
      "volume_24h_usd": 170585.10568,
      "volume_7d_usd": 1110781.27743,
      "apy_base": 23.88873,
      "apy_reward": 0,
      "apy_total": 23.88873,
      "il_risk": 0.5,
      "il_risk_label": "Medium",
      "risk_adjusted_apy": 17.31932925,
      "efficiency": 1.3089710380601596,
      "token0_type": "major",
      "token1_type": "major"
    }
  ]
}