{
  "timestamp": "2026-06-12T12:55:33.132112+00:00",
  "summary": {
    "timestamp": "2026-06-12T12:55:33.132112+00:00",
    "total_positions": 7,
    "positions_in_range": 7,
    "positions_out_of_range": 0,
    "total_balance_usd": 22807.615840281345,
    "total_uncollected_fees_usd": 295.576076748525,
    "by_chain": {
      "arbitrum": {
        "balance_usd": 7126.217400196436,
        "fees_usd": 29.723096417555144,
        "count": 2
      },
      "bsc": {
        "balance_usd": 15681.39844008491,
        "fees_usd": 265.85298033096984,
        "count": 5
      }
    },
    "by_wallet": {
      "MMA_1": {
        "balance_usd": 16997.51636574991,
        "fees_usd": 192.92010697986996,
        "count": 5
      },
      "MMA_3": {
        "balance_usd": 5810.099474531433,
        "fees_usd": 102.65596976865501,
        "count": 2
      }
    }
  },
  "positions": [
    {
      "wallet": "0x17e6D71D30d260e30BB7721C63539694aB02b036",
      "wallet_name": "MMA_1",
      "chain": "arbitrum",
      "token_id": 5529280,
      "pool_address": "0x641C00A822e8b671738d32a431a4Fb6074E5c79d",
      "token0_symbol": "WETH",
      "token1_symbol": "USD₮0",
      "token0_address": "0x82aF49447D8a07e3bd95BD0d56f35241523fBab1",
      "token1_address": "0xFd086bC7CD5C481DCC9C85ebE478A1C0b69FCbb9",
      "fee_tier": 0.05,
      "liquidity": 1452724416167703,
      "tick_lower": -202860,
      "tick_upper": -201940,
      "current_tick": -202131,
      "in_range": true,
      "amount0": 0.3381270762108334,
      "amount1": 2123.109107,
      "amount0_usd": 563.1607892414293,
      "amount1_usd": 2120.9966134385354,
      "balance_usd": 2684.1574026799644,
      "uncollected_fees0": 0.000549658138230065,
      "uncollected_fees1": 22.419279,
      "uncollected_fees_usd": 23.31244393636132,
      "price0_usd": 1665.53,
      "price1_usd": 0.999005,
      "range_width_pct": 8.95854152567686,
      "distance_to_lower_pct": 7.0302816728879804,
      "distance_to_upper_pct": 1.9282598527888797
    },
    {
      "wallet": "0x17e6D71D30d260e30BB7721C63539694aB02b036",
      "wallet_name": "MMA_1",
      "chain": "arbitrum",
      "token_id": 5529301,
      "pool_address": "0x2f5e87C9312fa29aed5c179E456625D79015299c",
      "token0_symbol": "WBTC",
      "token1_symbol": "WETH",
      "token0_address": "0x2f2a2543B76A4166549F7aaB2e75Bef0aefC5B0f",
      "token1_address": "0x82aF49447D8a07e3bd95BD0d56f35241523fBab1",
      "fee_tier": 0.05,
      "liquidity": 96130989111260,
      "tick_lower": 266170,
      "tick_upper": 267080,
      "current_tick": 266650,
      "in_range": true,
      "amount0": 0.0331263,
      "amount1": 1.4068461710185176,
      "amount0_usd": 2098.9154943,
      "amount1_usd": 2343.1445032164715,
      "balance_usd": 4442.059997516471,
      "uncollected_fees0": 0.00010043,
      "uncollected_fees1": 2.8403722054736e-05,
      "uncollected_fees_usd": 6.410652481193825,
      "price0_usd": 63361,
      "price1_usd": 1665.53,
      "range_width_pct": 9.079957608731242,
      "distance_to_lower_pct": 4.686392555114645,
      "distance_to_upper_pct": 4.393565053616596
    },
    {
      "wallet": "0x17e6D71D30d260e30BB7721C63539694aB02b036",
      "wallet_name": "MMA_1",
      "chain": "bsc",
      "token_id": 2271032,
      "pool_address": "0x4d1b90273d5B0Ea98101154D73A6C7D7A19884DB",
      "token0_symbol": "ZEC",
      "token1_symbol": "USDT",
      "token0_address": "0x1Ba42e5193dfA8B03D15dd1B86a3113bbBEF8Eeb",
      "token1_address": "0x55d398326f99059fF775485246999027B3197955",
      "fee_tier": 0.3,
      "liquidity": 2955634294431125696898,
      "tick_lower": 59940,
      "tick_upper": 61080,
      "current_tick": 60769,
      "in_range": true,
      "amount0": 2.1822938172975657,
      "amount1": 2505.602927853833,
      "amount0_usd": 947.7265589759868,
      "amount1_usd": 2502.473429796944,
      "balance_usd": 3450.1999887729307,
      "uncollected_fees0": 0.09411819262280946,
      "uncollected_fees1": 43.97082959341139,
      "uncollected_fees_usd": 84.7895587194829,
      "price0_usd": 434.28,
      "price1_usd": 0.998751,
      "range_width_pct": 11.114005165497495,
      "distance_to_lower_pct": 7.955299807264987,
      "distance_to_upper_pct": 3.158705358232508
    },
    {
      "wallet": "0x17e6D71D30d260e30BB7721C63539694aB02b036",
      "wallet_name": "MMA_1",
      "chain": "bsc",
      "token_id": 2271047,
      "pool_address": "0x4d1b90273d5B0Ea98101154D73A6C7D7A19884DB",
      "token0_symbol": "ZEC",
      "token1_symbol": "USDT",
      "token0_address": "0x1Ba42e5193dfA8B03D15dd1B86a3113bbBEF8Eeb",
      "token1_address": "0x55d398326f99059fF775485246999027B3197955",
      "fee_tier": 0.3,
      "liquidity": 2324459621973019434469,
      "tick_lower": 59880,
      "tick_upper": 61020,
      "current_tick": 60769,
      "in_range": true,
      "amount0": 1.38680467954373,
      "amount1": 2109.9396842512124,
      "amount0_usd": 602.261536232251,
      "amount1_usd": 2107.3043695855827,
      "balance_usd": 2709.5659058178335,
      "uncollected_fees0": 0.07324215146969025,
      "uncollected_fees1": 34.156749496834436,
      "uncollected_fees_usd": 65.92168925696997,
      "price0_usd": 434.28,
      "price1_usd": 0.998751,
      "range_width_pct": 11.04752410112855,
      "distance_to_lower_pct": 8.505887066062606,
      "distance_to_upper_pct": 2.5416370350659445
    },
    {
      "wallet": "0x17e6D71D30d260e30BB7721C63539694aB02b036",
      "wallet_name": "MMA_1",
      "chain": "bsc",
      "token_id": 2273383,
      "pool_address": "0x30Db6DFDb8817765797bd62316e41F5f4E431E93",
      "token0_symbol": "ASTER",
      "token1_symbol": "USDT",
      "token0_address": "0x000Ae314E2A2172a039B26378814C252734f556A",
      "token1_address": "0x55d398326f99059fF775485246999027B3197955",
      "fee_tier": 0.3,
      "liquidity": 157399471735851064877590,
      "tick_lower": -4920,
      "tick_upper": -4320,
      "current_tick": -4657,
      "in_range": true,
      "amount0": 3314.1511044597705,
      "amount1": 1632.2915377948905,
      "amount0_usd": 2081.280265298527,
      "amount1_usd": 1630.2528056641847,
      "balance_usd": 3711.5330709627115,
      "uncollected_fees0": 10.575755222306276,
      "uncollected_fees1": 5.851518003750752,
      "uncollected_fees_usd": 12.485762585861963,
      "price0_usd": 0.627998,
      "price1_usd": 0.998751,
      "range_width_pct": 6.022842155888511,
      "distance_to_lower_pct": 2.5955886295652935,
      "distance_to_upper_pct": 3.4272535263232173
    },
    {
      "wallet": "0x3c2c34B9bB0b00145142FFeE68475E1AC01C92bA",
      "wallet_name": "MMA_3",
      "chain": "bsc",
      "token_id": 2270140,
      "pool_address": "0x4d1b90273d5B0Ea98101154D73A6C7D7A19884DB",
      "token0_symbol": "ZEC",
      "token1_symbol": "USDT",
      "token0_address": "0x1Ba42e5193dfA8B03D15dd1B86a3113bbBEF8Eeb",
      "token1_address": "0x55d398326f99059fF775485246999027B3197955",
      "fee_tier": 0.3,
      "liquidity": 3294493946659913689032,
      "tick_lower": 60060,
      "tick_upper": 61080,
      "current_tick": 60769,
      "in_range": true,
      "amount0": 2.432490983226992,
      "amount1": 2395.9157845491036,
      "amount0_usd": 1056.382184195818,
      "amount1_usd": 2392.9232857342017,
      "balance_usd": 3449.3054699300196,
      "uncollected_fees0": 0.10422292478687788,
      "uncollected_fees1": 48.637374767710625,
      "uncollected_fees_usd": 93.83855846307108,
      "price0_usd": 434.28,
      "price1_usd": 0.998751,
      "range_width_pct": 10.002870845970927,
      "distance_to_lower_pct": 6.844165487738419,
      "distance_to_upper_pct": 3.158705358232508
    },
    {
      "wallet": "0x3c2c34B9bB0b00145142FFeE68475E1AC01C92bA",
      "wallet_name": "MMA_3",
      "chain": "bsc",
      "token_id": 2273402,
      "pool_address": "0x30Db6DFDb8817765797bd62316e41F5f4E431E93",
      "token0_symbol": "ASTER",
      "token1_symbol": "USDT",
      "token0_address": "0x000Ae314E2A2172a039B26378814C252734f556A",
      "token1_address": "0x55d398326f99059fF775485246999027B3197955",
      "fee_tier": 0.3,
      "liquidity": 111155075393484374388271,
      "tick_lower": -4920,
      "tick_upper": -4380,
      "current_tick": -4657,
      "in_range": true,
      "amount0": 1925.9837498677061,
      "amount1": 1152.7198086930514,
      "amount0_usd": 1209.5139429494195,
      "amount1_usd": 1151.280061651994,
      "balance_usd": 2360.7940046014137,
      "uncollected_fees0": 7.468569342159577,
      "uncollected_fees1": 4.132325970984169,
      "uncollected_fees_usd": 8.817411305583938,
      "price0_usd": 0.627998,
      "price1_usd": 0.998751,
      "range_width_pct": 5.404167448004371,
      "distance_to_lower_pct": 2.5955886295652935,
      "distance_to_upper_pct": 2.808578818439077
    }
  ]
}